src/pycat/__init__.py
src/pycat/__main__.py
simple_tcp_client-0.0.5.dist-info/METADATA
simple_tcp_client-0.0.5.dist-info/WHEEL
simple_tcp_client-0.0.5.dist-info/entry_points.txt
simple_tcp_client-0.0.5.dist-info/licenses/LICENSE
simple_tcp_client-0.0.5.dist-info/RECORD
