Metadata-Version: 2.1
Name: simple-tcp-client
Version: 0.0.5
Summary: Simple commnad line TCP client
Project-URL: Homepage, https://gitlab.cylab.be/cylab/pycat
Project-URL: Bug Tracker, https://gitlab.cylab.be/cylab/pycat/-/issues
Author-email: Thibault Debatty <t.debatty@cylab.be>
License-File: LICENSE
Classifier: License :: OSI Approved :: MIT License
Classifier: Operating System :: OS Independent
Classifier: Programming Language :: Python :: 3
Requires-Python: >=3.7
Requires-Dist: validators
